pisslang/__init__.py
pisslang-0.0.0.5.dist-info/LICENCE
pisslang-0.0.0.5.dist-info/METADATA
pisslang-0.0.0.5.dist-info/WHEEL
pisslang-0.0.0.5.dist-info/top_level.txt
pisslang-0.0.0.5.dist-info/RECORD
